{
	"elevators": [
		{
			"id": "Elevator-1",
			"currentFloor": 0,
			"destinationFloor": 0,
			"peopleAmount": 0,
			"working": false
		}, {
			"id": "Elevator-2",
			"currentFloor": 0,
			"destinationFloor": 0,
			"peopleAmount": 0,
			"working": true
		}, {
			"id": "Elevator-3",
			"currentFloor": 0,
			"destinationFloor": 0,
			"peopleAmount": 0,
			"working": true
		}, {
			"id": "Elevator-4",
			"currentFloor": 0,
			"destinationFloor": 0,
			"peopleAmount": 0,
			"working": true
		}, {
			"id": "Elevator-5",
			"currentFloor": 0,
			"destinationFloor": 0,
			"peopleAmount": 0,
			"working": true
		}
	]
}
